socket_logging/__init__.py
socket_logging/client.py
socket_logging/server.py
socket_logging/utils.py
mp_socket_logging-0.1.1.dist-info/LICENSE
mp_socket_logging-0.1.1.dist-info/METADATA
mp_socket_logging-0.1.1.dist-info/WHEEL
mp_socket_logging-0.1.1.dist-info/top_level.txt
mp_socket_logging-0.1.1.dist-info/RECORD
