Metadata-Version: 2.1
Name: mp-socket-logging
Version: 0.1.1
Summary: A small toolkit for python multiprocessing file logging
Home-page: https://github.com/FerdinandZhong/mp-socket-logging
Author: Zhong Qishuai
Author-email: ferdinandzhong@gmail.com
License: UNKNOWN
Platform: UNKNOWN
Classifier: Programming Language :: Python :: 3
Requires-Python: >3
License-File: LICENSE
Provides-Extra: dev
Requires-Dist: pytest (>=6) ; extra == 'dev'
Requires-Dist: flake8 (>=3.8) ; extra == 'dev'
Requires-Dist: black (>=20.8b1) ; extra == 'dev'
Requires-Dist: isort (>=5.6) ; extra == 'dev'
Requires-Dist: autoflake (>=1.4) ; extra == 'dev'
